<?xml version="1.0" ?>
<DeviceTree>
	<Device Desc="" DevInst="1" Lev="0">
		<DevInfo>
			<DevId>HTREE\ROOT\0</DevId>
			<Driver></Driver>
			<Class></Class>
			<Mfg></Mfg>
			<FriendlyName></FriendlyName>
			<ComPort></ComPort>
			<CompatIds></CompatIds>
		</DevInfo>
		<Device Desc="卷管理器" DevInst="2" Lev="1">
			<DevInfo>
				<DevId>ROOT\VOLMGR\0000</DevId>
				<Driver>{4d36e97d-e325-11ce-bfc1-08002be10318}\0027</Driver>
				<Class>System</Class>
				<Mfg>Microsoft</Mfg>
				<FriendlyName></FriendlyName>
				<ComPort></ComPort>
				<CompatIds>DETECTEDInternal\volmgr
DETECTED\volmgr</CompatIds>
			</DevInfo>
			<Device Desc="卷" DevInst="3" Lev="2">
				<DevInfo>
					<DevId>STORAGE\VOLUME\{4A3DE023-F27F-11E5-9BC6-806E6F6E6963}#0000000000200000</DevId>
					<Driver>{71a27cdd-812a-11d0-bec7-08002be2092f}\0002</Driver>
					<Class>Volume</Class>
					<Mfg>Microsoft</Mfg>
					<FriendlyName></FriendlyName>
					<ComPort></ComPort>
					<CompatIds></CompatIds>
				</DevInfo>
			</Device>
			<Device Desc="卷" DevInst="4" Lev="2">
				<DevInfo>
					<DevId>STORAGE\VOLUME\{4A3DE023-F27F-11E5-9BC6-806E6F6E6963}#0000000B22400000</DevId>
					<Driver>{71a27cdd-812a-11d0-bec7-08002be2092f}\0003</Driver>
					<Class>Volume</Class>
					<Mfg>Microsoft</Mfg>
					<FriendlyName></FriendlyName>
					<ComPort></ComPort>
					<CompatIds></CompatIds>
				</DevInfo>
			</Device>
		</Device>
		<Device Desc="Microsoft 基本显示驱动程序" DevInst="5" Lev="1">
			<DevInfo>
				<DevId>ROOT\BASICDISPLAY\0000</DevId>
				<Driver>{4d36e97d-e325-11ce-bfc1-08002be10318}\0028</Driver>
				<Class>System</Class>
				<Mfg>(标准显示器类型)</Mfg>
				<FriendlyName></FriendlyName>
				<ComPort></ComPort>
				<CompatIds></CompatIds>
			</DevInfo>
		</Device>
		<Device Desc="复合总线枚举器" DevInst="6" Lev="1">
			<DevInfo>
				<DevId>ROOT\COMPOSITEBUS\0000</DevId>
				<Driver>{4d36e97d-e325-11ce-bfc1-08002be10318}\0000</Driver>
				<Class>System</Class>
				<Mfg>Microsoft</Mfg>
				<FriendlyName></FriendlyName>
				<ComPort></ComPort>
				<CompatIds></CompatIds>
			</DevInfo>
		</Device>
		<Device Desc="Microsoft 虚拟驱动器枚举器" DevInst="7" Lev="1">
			<DevInfo>
				<DevId>ROOT\VDRVROOT\0000</DevId>
				<Driver>{4d36e97d-e325-11ce-bfc1-08002be10318}\0026</Driver>
				<Class>System</Class>
				<Mfg>Microsoft</Mfg>
				<FriendlyName></FriendlyName>
				<ComPort></ComPort>
				<CompatIds></CompatIds>
			</DevInfo>
		</Device>
		<Device Desc="Microsoft 存储空间控制器" DevInst="8" Lev="1">
			<DevInfo>
				<DevId>ROOT\SPACEPORT\0000</DevId>
				<Driver>{4d36e97b-e325-11ce-bfc1-08002be10318}\0000</Driver>
				<Class>SCSIAdapter</Class>
				<Mfg>Microsoft</Mfg>
				<FriendlyName></FriendlyName>
				<ComPort></ComPort>
				<CompatIds>DETECTEDInternal\spaceport
DETECTED\spaceport</CompatIds>
			</DevInfo>
		</Device>
		<Device Desc="Microsoft 内核调试网络适配器" DevInst="9" Lev="1">
			<DevInfo>
				<DevId>ROOT\KDNIC\0000</DevId>
				<Driver>{4d36e972-e325-11ce-bfc1-08002be10318}\0001</Driver>
				<Class>Net</Class>
				<Mfg>Microsoft</Mfg>
				<FriendlyName>Microsoft Kernel Debug Network Adapter</FriendlyName>
				<ComPort></ComPort>
				<CompatIds></CompatIds>
			</DevInfo>
		</Device>
		<Device Desc="UMBus Root Bus Enumerator" DevInst="10" Lev="1">
			<DevInfo>
				<DevId>ROOT\UMBUS\0000</DevId>
				<Driver>{4d36e97d-e325-11ce-bfc1-08002be10318}\0001</Driver>
				<Class>System</Class>
				<Mfg>Microsoft</Mfg>
				<FriendlyName></FriendlyName>
				<ComPort></ComPort>
				<CompatIds></CompatIds>
			</DevInfo>
		</Device>
		<Device Desc="基于 ACPI x64 的电脑" DevInst="11" Lev="1">
			<DevInfo>
				<DevId>ROOT\ACPI_HAL\0000</DevId>
				<Driver>{4d36e966-e325-11ce-bfc1-08002be10318}\0000</Driver>
				<Class>Computer</Class>
				<Mfg>(标准计算机)</Mfg>
				<FriendlyName></FriendlyName>
				<ComPort></ComPort>
				<CompatIds>DETECTEDInternal\ACPI_HAL
DETECTED\ACPI_HAL</CompatIds>
			</DevInfo>
			<Device Desc="Microsoft ACPI-Compliant System" DevInst="12" Lev="2">
				<DevInfo>
					<DevId>ACPI_HAL\PNP0C08\0</DevId>
					<Driver>{4d36e97d-e325-11ce-bfc1-08002be10318}\0005</Driver>
					<Class>System</Class>
					<Mfg>Microsoft</Mfg>
					<FriendlyName></FriendlyName>
					<ComPort></ComPort>
					<CompatIds></CompatIds>
				</DevInfo>
				<Device Desc="系统 CMOS/实时时钟" DevInst="13" Lev="3">
					<DevInfo>
						<DevId>ACPI\PNP0B00\2&amp;DABA3FF&amp;1</DevId>
						<Driver>{4d36e97d-e325-11ce-bfc1-08002be10318}\0006</Driver>
						<Class>System</Class>
						<Mfg>(标准系统设备)</Mfg>
						<FriendlyName></FriendlyName>
						<ComPort></ComPort>
						<CompatIds></CompatIds>
					</DevInfo>
				</Device>
				<Device Desc="PCI Express 根复合体" DevInst="14" Lev="3">
					<DevInfo>
						<DevId>ACPI\PNP0A08\0</DevId>
						<Driver>{4d36e97d-e325-11ce-bfc1-08002be10318}\0007</Driver>
						<Class>System</Class>
						<Mfg>(标准系统设备)</Mfg>
						<FriendlyName></FriendlyName>
						<ComPort></ComPort>
						<CompatIds>*PNP0A03</CompatIds>
					</DevInfo>
					<Device Desc="PCI 标准主机 CPU 桥" DevInst="15" Lev="4">
						<DevInfo>
							<DevId>PCI\VEN_8086&amp;DEV_2280&amp;SUBSYS_72708086&amp;REV_21\3&amp;11583659&amp;0&amp;00</DevId>
							<Driver>{4d36e97d-e325-11ce-bfc1-08002be10318}\0013</Driver>
							<Class>System</Class>
							<Mfg>(标准系统设备)</Mfg>
							<FriendlyName></FriendlyName>
							<ComPort></ComPort>
							<CompatIds>PCI\VEN_8086&amp;DEV_2280&amp;REV_21
PCI\VEN_8086&amp;DEV_2280
PCI\VEN_8086&amp;CC_060000
PCI\VEN_8086&amp;CC_0600
PCI\VEN_8086
PCI\CC_060000
PCI\CC_0600</CompatIds>
						</DevInfo>
					</Device>
					<Device Desc="Intel(R) HD Graphics" DevInst="16" Lev="4">
						<DevInfo>
							<DevId>PCI\VEN_8086&amp;DEV_22B1&amp;SUBSYS_72708086&amp;REV_21\3&amp;11583659&amp;0&amp;10</DevId>
							<Driver>{4d36e968-e325-11ce-bfc1-08002be10318}\0000</Driver>
							<Class>Display</Class>
							<Mfg>Intel Corporation</Mfg>
							<FriendlyName></FriendlyName>
							<ComPort></ComPort>
							<CompatIds>PCI\VEN_8086&amp;DEV_22B1&amp;REV_21
PCI\VEN_8086&amp;DEV_22B1
PCI\VEN_8086&amp;CC_030000
PCI\VEN_8086&amp;CC_0300
PCI\VEN_8086
PCI\CC_030000
PCI\CC_0300</CompatIds>
						</DevInfo>
						<Device Desc="数字平面显示器(1024x768 60Hz)" DevInst="17" Lev="5">
							<DevInfo>
								<DevId>DISPLAY\MS_0003\4&amp;1F74DE9F&amp;0&amp;UID265988</DevId>
								<Driver>{4d36e96e-e325-11ce-bfc1-08002be10318}\0000</Driver>
								<Class>Monitor</Class>
								<Mfg>(标准监视器类型)</Mfg>
								<FriendlyName></FriendlyName>
								<ComPort></ComPort>
								<CompatIds>*PNP09FF</CompatIds>
							</DevInfo>
						</Device>
						<Device Desc="BenQ EW2445ZH" DevInst="18" Lev="5">
							<DevInfo>
								<DevId>DISPLAY\BNQ7942\4&amp;1F74DE9F&amp;0&amp;UID198155</DevId>
								<Driver>{4d36e96e-e325-11ce-bfc1-08002be10318}\0001</Driver>
								<Class>Monitor</Class>
								<Mfg>BenQ</Mfg>
								<FriendlyName></FriendlyName>
								<ComPort></ComPort>
								<CompatIds>*PNP09FF</CompatIds>
							</DevInfo>
						</Device>
					</Device>
					<Device Desc="标准 SATA AHCI 控制器" DevInst="19" Lev="4">
						<DevInfo>
							<DevId>PCI\VEN_8086&amp;DEV_22A3&amp;SUBSYS_72708086&amp;REV_21\3&amp;11583659&amp;0&amp;98</DevId>
							<Driver>{4d36e96a-e325-11ce-bfc1-08002be10318}\0000</Driver>
							<Class>HDC</Class>
							<Mfg>标准 SATA AHCI 控制器</Mfg>
							<FriendlyName></FriendlyName>
							<ComPort></ComPort>
							<CompatIds>PCI\VEN_8086&amp;DEV_22A3&amp;REV_21
PCI\VEN_8086&amp;DEV_22A3
PCI\VEN_8086&amp;CC_010601
PCI\VEN_8086&amp;CC_0106
PCI\VEN_8086
PCI\CC_010601
PCI\CC_0106</CompatIds>
						</DevInfo>
						<Device Desc="磁盘驱动器" DevInst="20" Lev="5">
							<DevInfo>
								<DevId>SCSI\DISK&amp;VEN_SATA&amp;PROD_SSD\4&amp;394A36B&amp;0&amp;010000</DevId>
								<Driver>{4d36e967-e325-11ce-bfc1-08002be10318}\0000</Driver>
								<Class>DiskDrive</Class>
								<Mfg>(标准磁盘驱动器)</Mfg>
								<FriendlyName>SATA SSD</FriendlyName>
								<ComPort></ComPort>
								<CompatIds>SCSI\Disk
SCSI\RAW</CompatIds>
							</DevInfo>
						</Device>
					</Device>
					<Device Desc="符合 USB xHCI 的主机控制器" DevInst="21" Lev="4">
						<DevInfo>
							<DevId>PCI\VEN_8086&amp;DEV_22B5&amp;SUBSYS_72708086&amp;REV_21\3&amp;11583659&amp;0&amp;A0</DevId>
							<Driver>{36fc9e60-c465-11cf-8056-444553540000}\0000</Driver>
							<Class>USB</Class>
							<Mfg>通用 USB xHCI 主机控制器</Mfg>
							<FriendlyName>Intel(R) USB 3.0 可扩展主机控制器 - 1.0 (Microsoft)</FriendlyName>
							<ComPort></ComPort>
							<CompatIds>PCI\VEN_8086&amp;DEV_22B5&amp;REV_21
PCI\VEN_8086&amp;DEV_22B5
PCI\VEN_8086&amp;CC_0C0330
PCI\VEN_8086&amp;CC_0C03
PCI\VEN_8086
PCI\CC_0C0330
PCI\CC_0C03</CompatIds>
						</DevInfo>
						<Device Desc="USB 根集线器(xHCI)" DevInst="22" Lev="5">
							<DevInfo>
								<DevId>USB\ROOT_HUB30\4&amp;27AEFE67&amp;0&amp;0</DevId>
								<Driver>{36fc9e60-c465-11cf-8056-444553540000}\0001</Driver>
								<Class>USB</Class>
								<Mfg>(标准 USB 集线器)</Mfg>
								<FriendlyName></FriendlyName>
								<ComPort></ComPort>
								<CompatIds></CompatIds>
							</DevInfo>
							<Device Desc="通用 USB 集线器" DevInst="23" Lev="6">
								<DevInfo>
									<DevId>USB\VID_0424&amp;PID_2514\5&amp;DED9A49&amp;0&amp;5</DevId>
									<Driver>{36fc9e60-c465-11cf-8056-444553540000}\0002</Driver>
									<Class>USB</Class>
									<Mfg>(标准 USB 集线器)</Mfg>
									<FriendlyName></FriendlyName>
									<ComPort></ComPort>
									<CompatIds>USB\USB20_HUB</CompatIds>
								</DevInfo>
								<Device Desc="USB Composite Device" DevInst="24" Lev="7">
									<DevInfo>
										<DevId>USB\VID_04D9&amp;PID_A0CD\6&amp;6D7A6F6&amp;0&amp;1</DevId>
										<Driver>{36fc9e60-c465-11cf-8056-444553540000}\0003</Driver>
										<Class>USB</Class>
										<Mfg>(标准 USB 主控制器)</Mfg>
										<FriendlyName></FriendlyName>
										<ComPort></ComPort>
										<CompatIds>USB\DevClass_00&amp;SubClass_00&amp;Prot_00
USB\DevClass_00&amp;SubClass_00
USB\DevClass_00
USB\COMPOSITE</CompatIds>
									</DevInfo>
									<Device Desc="USB 输入设备" DevInst="25" Lev="8">
										<DevInfo>
											<DevId>USB\VID_04D9&amp;PID_A0CD&amp;MI_00\7&amp;17D55429&amp;0&amp;0000</DevId>
											<Driver>{745a17a0-74d3-11d0-b6fe-00a0c90f57da}\0000</Driver>
											<Class>HIDClass</Class>
											<Mfg>(标准系统设备)</Mfg>
											<FriendlyName></FriendlyName>
											<ComPort></ComPort>
											<CompatIds>USB\Class_03&amp;SubClass_01&amp;Prot_01
USB\Class_03&amp;SubClass_01
USB\Class_03</CompatIds>
										</DevInfo>
										<Device Desc="HID Keyboard Device" DevInst="26" Lev="9">
											<DevInfo>
												<DevId>HID\VID_04D9&amp;PID_A0CD&amp;MI_00\8&amp;319870C1&amp;0&amp;0000</DevId>
												<Driver>{4d36e96b-e325-11ce-bfc1-08002be10318}\0000</Driver>
												<Class>Keyboard</Class>
												<Mfg>(标准键盘)</Mfg>
												<FriendlyName></FriendlyName>
												<ComPort></ComPort>
												<CompatIds></CompatIds>
											</DevInfo>
										</Device>
									</Device>
									<Device Desc="USB 输入设备" DevInst="27" Lev="8">
										<DevInfo>
											<DevId>USB\VID_04D9&amp;PID_A0CD&amp;MI_01\7&amp;17D55429&amp;0&amp;0001</DevId>
											<Driver>{745a17a0-74d3-11d0-b6fe-00a0c90f57da}\0001</Driver>
											<Class>HIDClass</Class>
											<Mfg>(标准系统设备)</Mfg>
											<FriendlyName></FriendlyName>
											<ComPort></ComPort>
											<CompatIds>USB\Class_03&amp;SubClass_00&amp;Prot_00
USB\Class_03&amp;SubClass_00
USB\Class_03</CompatIds>
										</DevInfo>
										<Device Desc="HID Keyboard Device" DevInst="28" Lev="9">
											<DevInfo>
												<DevId>HID\VID_04D9&amp;PID_A0CD&amp;MI_01&amp;COL01\8&amp;DC132FF&amp;0&amp;0000</DevId>
												<Driver>{4d36e96b-e325-11ce-bfc1-08002be10318}\0001</Driver>
												<Class>Keyboard</Class>
												<Mfg>(标准键盘)</Mfg>
												<FriendlyName></FriendlyName>
												<ComPort></ComPort>
												<CompatIds></CompatIds>
											</DevInfo>
										</Device>
										<Device Desc="符合 HID 标准的系统控制器" DevInst="29" Lev="9">
											<DevInfo>
												<DevId>HID\VID_04D9&amp;PID_A0CD&amp;MI_01&amp;COL02\8&amp;DC132FF&amp;0&amp;0001</DevId>
												<Driver>{745a17a0-74d3-11d0-b6fe-00a0c90f57da}\0003</Driver>
												<Class>HIDClass</Class>
												<Mfg>(标准系统设备)</Mfg>
												<FriendlyName></FriendlyName>
												<ComPort></ComPort>
												<CompatIds></CompatIds>
											</DevInfo>
										</Device>
										<Device Desc="符合 HID 标准的用户控制设备" DevInst="30" Lev="9">
											<DevInfo>
												<DevId>HID\VID_04D9&amp;PID_A0CD&amp;MI_01&amp;COL03\8&amp;DC132FF&amp;0&amp;0002</DevId>
												<Driver>{745a17a0-74d3-11d0-b6fe-00a0c90f57da}\0004</Driver>
												<Class>HIDClass</Class>
												<Mfg>Microsoft</Mfg>
												<FriendlyName></FriendlyName>
												<ComPort></ComPort>
												<CompatIds></CompatIds>
											</DevInfo>
										</Device>
										<Device Desc="符合 HID 标准的供应商定义设备" DevInst="31" Lev="9">
											<DevInfo>
												<DevId>HID\VID_04D9&amp;PID_A0CD&amp;MI_01&amp;COL04\8&amp;DC132FF&amp;0&amp;0003</DevId>
												<Driver>{745a17a0-74d3-11d0-b6fe-00a0c90f57da}\0005</Driver>
												<Class>HIDClass</Class>
												<Mfg>(标准系统设备)</Mfg>
												<FriendlyName></FriendlyName>
												<ComPort></ComPort>
												<CompatIds></CompatIds>
											</DevInfo>
										</Device>
										<Device Desc="符合 HID 标准的供应商定义设备" DevInst="32" Lev="9">
											<DevInfo>
												<DevId>HID\VID_04D9&amp;PID_A0CD&amp;MI_01&amp;COL05\8&amp;DC132FF&amp;0&amp;0004</DevId>
												<Driver>{745a17a0-74d3-11d0-b6fe-00a0c90f57da}\0006</Driver>
												<Class>HIDClass</Class>
												<Mfg>(标准系统设备)</Mfg>
												<FriendlyName></FriendlyName>
												<ComPort></ComPort>
												<CompatIds></CompatIds>
											</DevInfo>
										</Device>
									</Device>
									<Device Desc="USB 输入设备" DevInst="33" Lev="8">
										<DevInfo>
											<DevId>USB\VID_04D9&amp;PID_A0CD&amp;MI_02\7&amp;17D55429&amp;0&amp;0002</DevId>
											<Driver>{745a17a0-74d3-11d0-b6fe-00a0c90f57da}\0002</Driver>
											<Class>HIDClass</Class>
											<Mfg>(标准系统设备)</Mfg>
											<FriendlyName></FriendlyName>
											<ComPort></ComPort>
											<CompatIds>USB\Class_03&amp;SubClass_00&amp;Prot_00
USB\Class_03&amp;SubClass_00
USB\Class_03</CompatIds>
										</DevInfo>
										<Device Desc="符合 HID 标准的供应商定义设备" DevInst="34" Lev="9">
											<DevInfo>
												<DevId>HID\VID_04D9&amp;PID_A0CD&amp;MI_02\8&amp;2584BF44&amp;0&amp;0000</DevId>
												<Driver>{745a17a0-74d3-11d0-b6fe-00a0c90f57da}\0007</Driver>
												<Class>HIDClass</Class>
												<Mfg>(标准系统设备)</Mfg>
												<FriendlyName></FriendlyName>
												<ComPort></ComPort>
												<CompatIds></CompatIds>
											</DevInfo>
										</Device>
									</Device>
								</Device>
								<Device Desc="USB 输入设备" DevInst="35" Lev="7">
									<DevInfo>
										<DevId>USB\VID_1C4F&amp;PID_0065\6&amp;6D7A6F6&amp;0&amp;2</DevId>
										<Driver>{745a17a0-74d3-11d0-b6fe-00a0c90f57da}\0008</Driver>
										<Class>HIDClass</Class>
										<Mfg>(标准系统设备)</Mfg>
										<FriendlyName></FriendlyName>
										<ComPort></ComPort>
										<CompatIds>USB\Class_03&amp;SubClass_01&amp;Prot_02
USB\Class_03&amp;SubClass_01
USB\Class_03</CompatIds>
									</DevInfo>
									<Device Desc="HID-compliant mouse" DevInst="36" Lev="8">
										<DevInfo>
											<DevId>HID\VID_1C4F&amp;PID_0065\7&amp;3B6D5AEC&amp;0&amp;0000</DevId>
											<Driver>{4d36e96f-e325-11ce-bfc1-08002be10318}\0000</Driver>
											<Class>Mouse</Class>
											<Mfg>Microsoft</Mfg>
											<FriendlyName></FriendlyName>
											<ComPort></ComPort>
											<CompatIds></CompatIds>
										</DevInfo>
									</Device>
								</Device>
							</Device>
						</Device>
					</Device>
					<Device Desc="Intel(R) Trusted Execution Engine Interface " DevInst="37" Lev="4">
						<DevInfo>
							<DevId>PCI\VEN_8086&amp;DEV_2298&amp;SUBSYS_72708086&amp;REV_21\3&amp;11583659&amp;0&amp;D0</DevId>
							<Driver>{4d36e97d-e325-11ce-bfc1-08002be10318}\0032</Driver>
							<Class>System</Class>
							<Mfg>Intel</Mfg>
							<FriendlyName></FriendlyName>
							<ComPort></ComPort>
							<CompatIds>PCI\VEN_8086&amp;DEV_2298&amp;REV_21
PCI\VEN_8086&amp;DEV_2298
PCI\VEN_8086&amp;CC_108000
PCI\VEN_8086&amp;CC_1080
PCI\VEN_8086
PCI\CC_108000
PCI\CC_1080</CompatIds>
						</DevInfo>
					</Device>
					<Device Desc="High Definition Audio 控制器" DevInst="38" Lev="4">
						<DevInfo>
							<DevId>PCI\VEN_8086&amp;DEV_2284&amp;SUBSYS_72708086&amp;REV_21\3&amp;11583659&amp;0&amp;D8</DevId>
							<Driver>{4d36e97d-e325-11ce-bfc1-08002be10318}\0014</Driver>
							<Class>System</Class>
							<Mfg>Microsoft</Mfg>
							<FriendlyName></FriendlyName>
							<ComPort></ComPort>
							<CompatIds>PCI\VEN_8086&amp;DEV_2284&amp;REV_21
PCI\VEN_8086&amp;DEV_2284
PCI\VEN_8086&amp;CC_040300
PCI\VEN_8086&amp;CC_0403
PCI\VEN_8086
PCI\CC_040300
PCI\CC_0403</CompatIds>
						</DevInfo>
						<Device Desc="Realtek High Definition Audio" DevInst="39" Lev="5">
							<DevInfo>
								<DevId>HDAUDIO\FUNC_01&amp;VEN_10EC&amp;DEV_0662&amp;SUBSYS_10EC0000&amp;REV_1003\4&amp;18168AEB&amp;0&amp;0001</DevId>
								<Driver>{4d36e96c-e325-11ce-bfc1-08002be10318}\0000</Driver>
								<Class>MEDIA</Class>
								<Mfg>Realtek</Mfg>
								<FriendlyName></FriendlyName>
								<ComPort></ComPort>
								<CompatIds></CompatIds>
							</DevInfo>
							<Device Desc="音频端点" DevInst="40" Lev="6">
								<DevInfo>
									<DevId>SWD\MMDEVAPI\{0.0.0.00000000}.{6DCA333B-D7BE-4C3E-8BF0-244273698D65}</DevId>
									<Driver>{c166523c-fe0c-4a94-a586-f1a80cfbbf3e}\0001</Driver>
									<Class>AudioEndpoint</Class>
									<Mfg>Microsoft</Mfg>
									<FriendlyName>扬声器 (Realtek High Definition Audio)</FriendlyName>
									<ComPort></ComPort>
									<CompatIds>GenericAudioEndpoint
SWD\GenericRaw
SWD\Generic</CompatIds>
								</DevInfo>
							</Device>
							<Device Desc="音频端点" DevInst="41" Lev="6">
								<DevInfo>
									<DevId>SWD\MMDEVAPI\{0.0.0.00000000}.{94D5EF2B-7A86-48B3-B1D0-CE87FEAD910A}</DevId>
									<Driver>{c166523c-fe0c-4a94-a586-f1a80cfbbf3e}\0000</Driver>
									<Class>AudioEndpoint</Class>
									<Mfg>Microsoft</Mfg>
									<FriendlyName>Realtek Digital Output (Realtek High Definition Audio)</FriendlyName>
									<ComPort></ComPort>
									<CompatIds>GenericAudioEndpoint
SWD\GenericRaw
SWD\Generic</CompatIds>
								</DevInfo>
							</Device>
							<Device Desc="音频端点" DevInst="42" Lev="6">
								<DevInfo>
									<DevId>SWD\MMDEVAPI\{0.0.1.00000000}.{04DE8697-D8A7-4719-A5A9-32FC144D82B5}</DevId>
									<Driver>{c166523c-fe0c-4a94-a586-f1a80cfbbf3e}\0002</Driver>
									<Class>AudioEndpoint</Class>
									<Mfg>Microsoft</Mfg>
									<FriendlyName>麦克风 (Realtek High Definition Audio)</FriendlyName>
									<ComPort></ComPort>
									<CompatIds>GenericAudioEndpoint
SWD\GenericRaw
SWD\Generic</CompatIds>
								</DevInfo>
							</Device>
						</Device>
						<Device Desc="英特尔(R) 显示器音频" DevInst="43" Lev="5">
							<DevInfo>
								<DevId>HDAUDIO\FUNC_01&amp;VEN_8086&amp;DEV_2883&amp;SUBSYS_80860101&amp;REV_1000\4&amp;18168AEB&amp;0&amp;0201</DevId>
								<Driver>{4d36e96c-e325-11ce-bfc1-08002be10318}\0001</Driver>
								<Class>MEDIA</Class>
								<Mfg>Intel(R) Corporation</Mfg>
								<FriendlyName></FriendlyName>
								<ComPort></ComPort>
								<CompatIds></CompatIds>
							</DevInfo>
							<Device Desc="音频端点" DevInst="44" Lev="6">
								<DevInfo>
									<DevId>SWD\MMDEVAPI\{0.0.0.00000000}.{89368978-46BF-4238-A00B-D00D8B7D62C6}</DevId>
									<Driver>{c166523c-fe0c-4a94-a586-f1a80cfbbf3e}\0003</Driver>
									<Class>AudioEndpoint</Class>
									<Mfg>Microsoft</Mfg>
									<FriendlyName>BenQ EW2445ZH (英特尔(R) 显示器音频)</FriendlyName>
									<ComPort></ComPort>
									<CompatIds>GenericAudioEndpoint
SWD\GenericRaw
SWD\Generic</CompatIds>
								</DevInfo>
							</Device>
						</Device>
					</Device>
					<Device Desc="PCI Express 根端口" DevInst="45" Lev="4">
						<DevInfo>
							<DevId>PCI\VEN_8086&amp;DEV_22C8&amp;SUBSYS_72708086&amp;REV_21\3&amp;11583659&amp;0&amp;E0</DevId>
							<Driver>{4d36e97d-e325-11ce-bfc1-08002be10318}\0015</Driver>
							<Class>System</Class>
							<Mfg>(标准系统设备)</Mfg>
							<FriendlyName></FriendlyName>
							<ComPort></ComPort>
							<CompatIds>PCI\VEN_8086&amp;DEV_22C8&amp;REV_21
PCI\VEN_8086&amp;DEV_22C8
PCI\VEN_8086&amp;CC_060400
PCI\VEN_8086&amp;CC_0604
PCI\VEN_8086
PCI\CC_060400&amp;DT_4
PCI\CC_060400
PCI\CC_0604&amp;DT_4
PCI\CC_0604</CompatIds>
						</DevInfo>
					</Device>
					<Device Desc="PCI Express 根端口" DevInst="46" Lev="4">
						<DevInfo>
							<DevId>PCI\VEN_8086&amp;DEV_22CA&amp;SUBSYS_72708086&amp;REV_21\3&amp;11583659&amp;0&amp;E1</DevId>
							<Driver>{4d36e97d-e325-11ce-bfc1-08002be10318}\0016</Driver>
							<Class>System</Class>
							<Mfg>(标准系统设备)</Mfg>
							<FriendlyName></FriendlyName>
							<ComPort></ComPort>
							<CompatIds>PCI\VEN_8086&amp;DEV_22CA&amp;REV_21
PCI\VEN_8086&amp;DEV_22CA
PCI\VEN_8086&amp;CC_060400
PCI\VEN_8086&amp;CC_0604
PCI\VEN_8086
PCI\CC_060400&amp;DT_4
PCI\CC_060400
PCI\CC_0604&amp;DT_4
PCI\CC_0604</CompatIds>
						</DevInfo>
						<Device Desc="Realtek PCIe GBE Family Controller" DevInst="47" Lev="5">
							<DevInfo>
								<DevId>PCI\VEN_10EC&amp;DEV_8168&amp;SUBSYS_012310EC&amp;REV_07\01000000684CE00000</DevId>
								<Driver>{4d36e972-e325-11ce-bfc1-08002be10318}\0002</Driver>
								<Class>Net</Class>
								<Mfg>Realtek</Mfg>
								<FriendlyName>Realtek PCIe GBE Family Controller #3</FriendlyName>
								<ComPort></ComPort>
								<CompatIds>PCI\VEN_10EC&amp;DEV_8168&amp;REV_07
PCI\VEN_10EC&amp;DEV_8168
PCI\VEN_10EC&amp;CC_020000
PCI\VEN_10EC&amp;CC_0200
PCI\VEN_10EC
PCI\CC_020000&amp;DT_0
PCI\CC_020000
PCI\CC_0200&amp;DT_0
PCI\CC_0200</CompatIds>
							</DevInfo>
						</Device>
					</Device>
					<Device Desc="PCI Express 根端口" DevInst="48" Lev="4">
						<DevInfo>
							<DevId>PCI\VEN_8086&amp;DEV_22CC&amp;SUBSYS_72708086&amp;REV_21\3&amp;11583659&amp;0&amp;E2</DevId>
							<Driver>{4d36e97d-e325-11ce-bfc1-08002be10318}\0017</Driver>
							<Class>System</Class>
							<Mfg>(标准系统设备)</Mfg>
							<FriendlyName></FriendlyName>
							<ComPort></ComPort>
							<CompatIds>PCI\VEN_8086&amp;DEV_22CC&amp;REV_21
PCI\VEN_8086&amp;DEV_22CC
PCI\VEN_8086&amp;CC_060400
PCI\VEN_8086&amp;CC_0604
PCI\VEN_8086
PCI\CC_060400&amp;DT_4
PCI\CC_060400
PCI\CC_0604&amp;DT_4
PCI\CC_0604</CompatIds>
						</DevInfo>
						<Device Desc="Dell Wireless 1502 802.11b|g|n" DevInst="49" Lev="5">
							<DevInfo>
								<DevId>PCI\VEN_168C&amp;DEV_002B&amp;SUBSYS_02041028&amp;REV_01\4&amp;4E1D5E1&amp;0&amp;00E2</DevId>
								<Driver>{4d36e972-e325-11ce-bfc1-08002be10318}\0000</Driver>
								<Class>Net</Class>
								<Mfg>Qualcomm Atheros Communications Inc.</Mfg>
								<FriendlyName>Dell Wireless 1502 802.11b|g|n</FriendlyName>
								<ComPort></ComPort>
								<CompatIds>PCI\VEN_168C&amp;DEV_002B&amp;REV_01
PCI\VEN_168C&amp;DEV_002B
PCI\VEN_168C&amp;CC_028000
PCI\VEN_168C&amp;CC_0280
PCI\VEN_168C
PCI\CC_028000&amp;DT_1
PCI\CC_028000
PCI\CC_0280&amp;DT_1
PCI\CC_0280</CompatIds>
							</DevInfo>
							<Device Desc="Microsoft 托管网络虚拟适配器" DevInst="50" Lev="6">
								<DevInfo>
									<DevId>{5D624F94-8850-40C3-A3FA-A4FD2080BAF3}\VWIFIMP_SAP\5&amp;6873C36&amp;0&amp;02</DevId>
									<Driver>{4d36e972-e325-11ce-bfc1-08002be10318}\0005</Driver>
									<Class>Net</Class>
									<Mfg>Microsoft</Mfg>
									<FriendlyName>Microsoft Hosted Network Virtual Adapter</FriendlyName>
									<ComPort></ComPort>
									<CompatIds>{5d624f94-8850-40c3-a3fa-a4fd2080baf3}\vwifimp_sap</CompatIds>
								</DevInfo>
							</Device>
							<Device Desc="Microsoft Wi-Fi Direct 虚拟适配器" DevInst="51" Lev="6">
								<DevInfo>
									<DevId>{5D624F94-8850-40C3-A3FA-A4FD2080BAF3}\VWIFIMP_WFD\5&amp;6873C36&amp;0&amp;01</DevId>
									<Driver>{4d36e972-e325-11ce-bfc1-08002be10318}\0004</Driver>
									<Class>Net</Class>
									<Mfg>Microsoft</Mfg>
									<FriendlyName>Microsoft Wi-Fi Direct Virtual Adapter #2</FriendlyName>
									<ComPort></ComPort>
									<CompatIds>{5d624f94-8850-40c3-a3fa-a4fd2080baf3}\vwifimp_wfd</CompatIds>
								</DevInfo>
							</Device>
						</Device>
					</Device>
					<Device Desc="PCI 标准 ISA 桥" DevInst="52" Lev="4">
						<DevInfo>
							<DevId>PCI\VEN_8086&amp;DEV_229C&amp;SUBSYS_72708086&amp;REV_21\3&amp;11583659&amp;0&amp;F8</DevId>
							<Driver>{4d36e97d-e325-11ce-bfc1-08002be10318}\0018</Driver>
							<Class>System</Class>
							<Mfg>(标准系统设备)</Mfg>
							<FriendlyName></FriendlyName>
							<ComPort></ComPort>
							<CompatIds>PCI\VEN_8086&amp;DEV_229C&amp;REV_21
PCI\VEN_8086&amp;DEV_229C
PCI\VEN_8086&amp;CC_060100
PCI\VEN_8086&amp;CC_0601
PCI\VEN_8086
PCI\CC_060100
PCI\CC_0601</CompatIds>
						</DevInfo>
						<Device Desc="旧设备" DevInst="53" Lev="5">
							<DevInfo>
								<DevId>ACPI\INT0800\4&amp;2DC7E78C&amp;0</DevId>
								<Driver>{4d36e97d-e325-11ce-bfc1-08002be10318}\0021</Driver>
								<Class>System</Class>
								<Mfg>Intel</Mfg>
								<FriendlyName></FriendlyName>
								<ComPort></ComPort>
								<CompatIds></CompatIds>
							</DevInfo>
						</Device>
						<Device Desc="可编程中断控制器" DevInst="54" Lev="5">
							<DevInfo>
								<DevId>ACPI\PNP0000\4&amp;2DC7E78C&amp;0</DevId>
								<Driver>{4d36e97d-e325-11ce-bfc1-08002be10318}\0022</Driver>
								<Class>System</Class>
								<Mfg>(标准系统设备)</Mfg>
								<FriendlyName></FriendlyName>
								<ComPort></ComPort>
								<CompatIds></CompatIds>
							</DevInfo>
						</Device>
						<Device Desc="母板资源" DevInst="55" Lev="5">
							<DevInfo>
								<DevId>ACPI\PNP0C02\2</DevId>
								<Driver>{4d36e97d-e325-11ce-bfc1-08002be10318}\0023</Driver>
								<Class>System</Class>
								<Mfg>(标准系统设备)</Mfg>
								<FriendlyName></FriendlyName>
								<ComPort></ComPort>
								<CompatIds></CompatIds>
							</DevInfo>
						</Device>
						<Device Desc="系统计时器" DevInst="56" Lev="5">
							<DevInfo>
								<DevId>ACPI\PNP0100\4&amp;2DC7E78C&amp;0</DevId>
								<Driver>{4d36e97d-e325-11ce-bfc1-08002be10318}\0024</Driver>
								<Class>System</Class>
								<Mfg>(标准系统设备)</Mfg>
								<FriendlyName></FriendlyName>
								<ComPort></ComPort>
								<CompatIds></CompatIds>
							</DevInfo>
						</Device>
						<Device Desc="Nuvoton SIO CIR Device Driver" DevInst="57" Lev="5">
							<DevInfo>
								<DevId>ACPI\NTN0530\4&amp;2DC7E78C&amp;0</DevId>
								<Driver>{745a17a0-74d3-11d0-b6fe-00a0c90f57da}\0009</Driver>
								<Class>HIDClass</Class>
								<Mfg>Nuvoton Technology Corp.</Mfg>
								<FriendlyName></FriendlyName>
								<ComPort></ComPort>
								<CompatIds></CompatIds>
							</DevInfo>
						</Device>
						<Device Desc="母板资源" DevInst="58" Lev="5">
							<DevInfo>
								<DevId>ACPI\PNP0C02\0</DevId>
								<Driver>{4d36e97d-e325-11ce-bfc1-08002be10318}\0025</Driver>
								<Class>System</Class>
								<Mfg>(标准系统设备)</Mfg>
								<FriendlyName></FriendlyName>
								<ComPort></ComPort>
								<CompatIds></CompatIds>
							</DevInfo>
						</Device>
						<Device Desc="通信端口" DevInst="59" Lev="5">
							<DevInfo>
								<DevId>ACPI\PNP0501\0</DevId>
								<Driver>{4d36e978-e325-11ce-bfc1-08002be10318}\0000</Driver>
								<Class>Ports</Class>
								<Mfg>(标准端口类型)</Mfg>
								<FriendlyName>通信端口 (COM1)</FriendlyName>
								<ComPort>COM1</ComPort>
								<CompatIds></CompatIds>
							</DevInfo>
						</Device>
					</Device>
					<Device Desc="Intel(R) Celeron(R)/Pentium(R) SM Bus Controller - 2292" DevInst="60" Lev="4">
						<DevInfo>
							<DevId>PCI\VEN_8086&amp;DEV_2292&amp;SUBSYS_72708086&amp;REV_21\3&amp;11583659&amp;0&amp;FB</DevId>
							<Driver>{4d36e97d-e325-11ce-bfc1-08002be10318}\0031</Driver>
							<Class>System</Class>
							<Mfg>INTEL</Mfg>
							<FriendlyName></FriendlyName>
							<ComPort></ComPort>
							<CompatIds>PCI\VEN_8086&amp;DEV_2292&amp;REV_21
PCI\VEN_8086&amp;DEV_2292
PCI\VEN_8086&amp;CC_0C0500
PCI\VEN_8086&amp;CC_0C05
PCI\VEN_8086
PCI\CC_0C0500
PCI\CC_0C05</CompatIds>
						</DevInfo>
					</Device>
					<Device Desc="母板资源" DevInst="61" Lev="4">
						<DevInfo>
							<DevId>ACPI\PNP0C02\3</DevId>
							<Driver>{4d36e97d-e325-11ce-bfc1-08002be10318}\0019</Driver>
							<Class>System</Class>
							<Mfg>(标准系统设备)</Mfg>
							<FriendlyName></FriendlyName>
							<ComPort></ComPort>
							<CompatIds></CompatIds>
						</DevInfo>
					</Device>
					<Device Desc="母板资源" DevInst="62" Lev="4">
						<DevInfo>
							<DevId>ACPI\PNP0C02\1</DevId>
							<Driver>{4d36e97d-e325-11ce-bfc1-08002be10318}\0020</Driver>
							<Class>System</Class>
							<Mfg>(标准系统设备)</Mfg>
							<FriendlyName></FriendlyName>
							<ComPort></ComPort>
							<CompatIds></CompatIds>
						</DevInfo>
					</Device>
				</Device>
				<Device Desc="Intel Processor" DevInst="63" Lev="3">
					<DevInfo>
						<DevId>ACPI\GENUINEINTEL_-_INTEL64_FAMILY_6_MODEL_76_-_______INTEL(R)_CELERON(R)_CPU__N3150__@_1.60GHZ\_1</DevId>
						<Driver>{50127dc3-0f36-415e-a6cc-4cb3be910b65}\0000</Driver>
						<Class>Processor</Class>
						<Mfg>Intel</Mfg>
						<FriendlyName>Intel(R) Celeron(R) CPU  N3150  @ 1.60GHz</FriendlyName>
						<ComPort></ComPort>
						<CompatIds>ACPI\Processor</CompatIds>
					</DevInfo>
				</Device>
				<Device Desc="Intel Processor" DevInst="64" Lev="3">
					<DevInfo>
						<DevId>ACPI\GENUINEINTEL_-_INTEL64_FAMILY_6_MODEL_76_-_______INTEL(R)_CELERON(R)_CPU__N3150__@_1.60GHZ\_2</DevId>
						<Driver>{50127dc3-0f36-415e-a6cc-4cb3be910b65}\0001</Driver>
						<Class>Processor</Class>
						<Mfg>Intel</Mfg>
						<FriendlyName>Intel(R) Celeron(R) CPU  N3150  @ 1.60GHz</FriendlyName>
						<ComPort></ComPort>
						<CompatIds>ACPI\Processor</CompatIds>
					</DevInfo>
				</Device>
				<Device Desc="Intel Processor" DevInst="65" Lev="3">
					<DevInfo>
						<DevId>ACPI\GENUINEINTEL_-_INTEL64_FAMILY_6_MODEL_76_-_______INTEL(R)_CELERON(R)_CPU__N3150__@_1.60GHZ\_3</DevId>
						<Driver>{50127dc3-0f36-415e-a6cc-4cb3be910b65}\0002</Driver>
						<Class>Processor</Class>
						<Mfg>Intel</Mfg>
						<FriendlyName>Intel(R) Celeron(R) CPU  N3150  @ 1.60GHz</FriendlyName>
						<ComPort></ComPort>
						<CompatIds>ACPI\Processor</CompatIds>
					</DevInfo>
				</Device>
				<Device Desc="Intel Processor" DevInst="66" Lev="3">
					<DevInfo>
						<DevId>ACPI\GENUINEINTEL_-_INTEL64_FAMILY_6_MODEL_76_-_______INTEL(R)_CELERON(R)_CPU__N3150__@_1.60GHZ\_4</DevId>
						<Driver>{50127dc3-0f36-415e-a6cc-4cb3be910b65}\0003</Driver>
						<Class>Processor</Class>
						<Mfg>Intel</Mfg>
						<FriendlyName>Intel(R) Celeron(R) CPU  N3150  @ 1.60GHz</FriendlyName>
						<ComPort></ComPort>
						<CompatIds>ACPI\Processor</CompatIds>
					</DevInfo>
				</Device>
				<Device Desc="ACPI 睡眠按钮" DevInst="67" Lev="3">
					<DevInfo>
						<DevId>ACPI\PNP0C0E\2&amp;DABA3FF&amp;1</DevId>
						<Driver>{4d36e97d-e325-11ce-bfc1-08002be10318}\0008</Driver>
						<Class>System</Class>
						<Mfg>(标准系统设备)</Mfg>
						<FriendlyName></FriendlyName>
						<ComPort></ComPort>
						<CompatIds></CompatIds>
					</DevInfo>
				</Device>
				<Device Desc="ACPI 盖子" DevInst="68" Lev="3">
					<DevInfo>
						<DevId>ACPI\PNP0C0D\2&amp;DABA3FF&amp;1</DevId>
						<Driver>{4d36e97d-e325-11ce-bfc1-08002be10318}\0009</Driver>
						<Class>System</Class>
						<Mfg>(标准系统设备)</Mfg>
						<FriendlyName></FriendlyName>
						<ComPort></ComPort>
						<CompatIds></CompatIds>
					</DevInfo>
				</Device>
				<Device Desc="ACPI 风扇" DevInst="69" Lev="3">
					<DevInfo>
						<DevId>ACPI\PNP0C0B\0</DevId>
						<Driver>{4d36e97d-e325-11ce-bfc1-08002be10318}\0010</Driver>
						<Class>System</Class>
						<Mfg>(标准系统设备)</Mfg>
						<FriendlyName></FriendlyName>
						<ComPort></ComPort>
						<CompatIds></CompatIds>
					</DevInfo>
				</Device>
				<Device Desc="ACPI 热区域" DevInst="70" Lev="3">
					<DevInfo>
						<DevId>ACPI\THERMALZONE\TZ01</DevId>
						<Driver>{4d36e97d-e325-11ce-bfc1-08002be10318}\0011</Driver>
						<Class>System</Class>
						<Mfg>(标准系统设备)</Mfg>
						<FriendlyName></FriendlyName>
						<ComPort></ComPort>
						<CompatIds></CompatIds>
					</DevInfo>
				</Device>
				<Device Desc="ACPI 固定功能按钮" DevInst="71" Lev="3">
					<DevInfo>
						<DevId>ACPI\FIXEDBUTTON\2&amp;DABA3FF&amp;1</DevId>
						<Driver>{4d36e97d-e325-11ce-bfc1-08002be10318}\0012</Driver>
						<Class>System</Class>
						<Mfg>(标准系统设备)</Mfg>
						<FriendlyName></FriendlyName>
						<ComPort></ComPort>
						<CompatIds></CompatIds>
					</DevInfo>
				</Device>
			</Device>
		</Device>
		<Device Desc="Microsoft 基本呈现驱动程序" DevInst="72" Lev="1">
			<DevInfo>
				<DevId>ROOT\BASICRENDER\0000</DevId>
				<Driver>{4d36e97d-e325-11ce-bfc1-08002be10318}\0029</Driver>
				<Class>System</Class>
				<Mfg>Microsoft</Mfg>
				<FriendlyName></FriendlyName>
				<ComPort></ComPort>
				<CompatIds></CompatIds>
			</DevInfo>
		</Device>
		<Device Desc="NDIS 虚拟网络适配器枚举器" DevInst="73" Lev="1">
			<DevInfo>
				<DevId>ROOT\NDISVIRTUALBUS\0000</DevId>
				<Driver>{4d36e97d-e325-11ce-bfc1-08002be10318}\0002</Driver>
				<Class>System</Class>
				<Mfg>Microsoft</Mfg>
				<FriendlyName></FriendlyName>
				<ComPort></ComPort>
				<CompatIds></CompatIds>
			</DevInfo>
		</Device>
		<Device Desc="IVT Bluetooth PAN Bus Driver" DevInst="74" Lev="1">
			<DevInfo>
				<DevId>ROOT\BLUETOOTH_DEVICE\0000</DevId>
				<Driver>{d2de069d-7286-420b-baf8-225d700ce748}\0000</Driver>
				<Class>Bluetooth Device</Class>
				<Mfg>IVT Corporation</Mfg>
				<FriendlyName></FriendlyName>
				<ComPort></ComPort>
				<CompatIds></CompatIds>
			</DevInfo>
			<Device Desc="Bluetooth PAN Network Adapter" DevInst="75" Lev="2">
				<DevInfo>
					<DevId>{F12D3CF8-B11D-457E-8641-BE2AF2D6D204}\IVTBTPAN\1&amp;1EC31360&amp;2&amp;0000</DevId>
					<Driver>{4d36e972-e325-11ce-bfc1-08002be10318}\0017</Driver>
					<Class>Net</Class>
					<Mfg>IVT Corporation</Mfg>
					<FriendlyName>Bluetooth PAN Network Adapter</FriendlyName>
					<ComPort></ComPort>
					<CompatIds>{F12D3CF8-B11D-457e-8641-BE2AF2D6D204}\IVTBthCompatibleDevice</CompatIds>
				</DevInfo>
			</Device>
		</Device>
		<Device Desc="IVT Bluetooth HID Bus Driver" DevInst="76" Lev="1">
			<DevInfo>
				<DevId>ROOT\BLUETOOTH_DEVICE\0001</DevId>
				<Driver>{d2de069d-7286-420b-baf8-225d700ce748}\0001</Driver>
				<Class>Bluetooth Device</Class>
				<Mfg>IVT Corporation</Mfg>
				<FriendlyName></FriendlyName>
				<ComPort></ComPort>
				<CompatIds></CompatIds>
			</DevInfo>
		</Device>
		<Device Desc="IVT Bluetooth COM Bus Driver" DevInst="77" Lev="1">
			<DevInfo>
				<DevId>ROOT\BLUETOOTH_DEVICE\0002</DevId>
				<Driver>{d2de069d-7286-420b-baf8-225d700ce748}\0002</Driver>
				<Class>Bluetooth Device</Class>
				<Mfg>IVT Corporation</Mfg>
				<FriendlyName></FriendlyName>
				<ComPort></ComPort>
				<CompatIds></CompatIds>
			</DevInfo>
			<Device Desc="Bluetooth Serial Port" DevInst="78" Lev="2">
				<DevInfo>
					<DevId>{F12D3CF8-B11D-457E-8641-BE2AF2D6D204}\COMPORT\1&amp;34EA7C1D&amp;2&amp;0001</DevId>
					<Driver>{4d36e978-e325-11ce-bfc1-08002be10318}\0001</Driver>
					<Class>Ports</Class>
					<Mfg>IVT Corporation</Mfg>
					<FriendlyName>Bluetooth Serial Port (COM3)</FriendlyName>
					<ComPort>COM3</ComPort>
					<CompatIds>{F12D3CF8-B11D-457e-8641-BE2AF2D6D204}\Bluetooth_ComPort</CompatIds>
				</DevInfo>
			</Device>
			<Device Desc="Bluetooth Serial Port" DevInst="79" Lev="2">
				<DevInfo>
					<DevId>{F12D3CF8-B11D-457E-8641-BE2AF2D6D204}\COMPORT\1&amp;34EA7C1D&amp;2&amp;0002</DevId>
					<Driver>{4d36e978-e325-11ce-bfc1-08002be10318}\0002</Driver>
					<Class>Ports</Class>
					<Mfg>IVT Corporation</Mfg>
					<FriendlyName>Bluetooth Serial Port (COM5)</FriendlyName>
					<ComPort>COM5</ComPort>
					<CompatIds>{F12D3CF8-B11D-457e-8641-BE2AF2D6D204}\Bluetooth_ComPort</CompatIds>
				</DevInfo>
			</Device>
		</Device>
		<Device Desc="IVT Bluetooth Audio Bus Driver" DevInst="80" Lev="1">
			<DevInfo>
				<DevId>ROOT\BLUETOOTH_DEVICE\0003</DevId>
				<Driver>{d2de069d-7286-420b-baf8-225d700ce748}\0003</Driver>
				<Class>Bluetooth Device</Class>
				<Mfg>IVT Corporation</Mfg>
				<FriendlyName></FriendlyName>
				<ComPort></ComPort>
				<CompatIds></CompatIds>
			</DevInfo>
		</Device>
		<Device Desc="Microsoft System Management BIOS Driver" DevInst="81" Lev="1">
			<DevInfo>
				<DevId>ROOT\MSSMBIOS\0000</DevId>
				<Driver>{4d36e97d-e325-11ce-bfc1-08002be10318}\0030</Driver>
				<Class>System</Class>
				<Mfg>(标准系统设备)</Mfg>
				<FriendlyName></FriendlyName>
				<ComPort></ComPort>
				<CompatIds></CompatIds>
			</DevInfo>
		</Device>
		<Device Desc="即插即用软件设备枚举器" DevInst="82" Lev="1">
			<DevInfo>
				<DevId>ROOT\SYSTEM\0000</DevId>
				<Driver>{4d36e97d-e325-11ce-bfc1-08002be10318}\0003</Driver>
				<Class>System</Class>
				<Mfg>(标准系统设备)</Mfg>
				<FriendlyName></FriendlyName>
				<ComPort></ComPort>
				<CompatIds></CompatIds>
			</DevInfo>
		</Device>
		<Device Desc="Consumer IR Devices" DevInst="83" Lev="1">
			<DevInfo>
				<DevId>ROOT\SYSTEM\0001</DevId>
				<Driver>{4d36e97d-e325-11ce-bfc1-08002be10318}\0033</Driver>
				<Class>System</Class>
				<Mfg>Microsoft</Mfg>
				<FriendlyName></FriendlyName>
				<ComPort></ComPort>
				<CompatIds></CompatIds>
			</DevInfo>
			<Device Desc="Microsoft eHome 红外线收发器" DevInst="84" Lev="2">
				<DevInfo>
					<DevId>CIRCLASS\IRDEVICEV2\1&amp;79F5D87&amp;0&amp;PORT1</DevId>
					<Driver>{745a17a0-74d3-11d0-b6fe-00a0c90f57da}\0010</Driver>
					<Class>HIDClass</Class>
					<Mfg>Microsoft</Mfg>
					<FriendlyName></FriendlyName>
					<ComPort></ComPort>
					<CompatIds></CompatIds>
				</DevInfo>
				<Device Desc="符合 HID 标准的供应商定义设备" DevInst="85" Lev="3">
					<DevInfo>
						<DevId>HID\IRDEVICEV2&amp;COL01\2&amp;2818A073&amp;0&amp;0000</DevId>
						<Driver>{745a17a0-74d3-11d0-b6fe-00a0c90f57da}\0011</Driver>
						<Class>HIDClass</Class>
						<Mfg>(标准系统设备)</Mfg>
						<FriendlyName></FriendlyName>
						<ComPort></ComPort>
						<CompatIds></CompatIds>
					</DevInfo>
				</Device>
				<Device Desc="符合 HID 标准的用户控制设备" DevInst="86" Lev="3">
					<DevInfo>
						<DevId>HID\IRDEVICEV2&amp;COL02\2&amp;2818A073&amp;0&amp;0001</DevId>
						<Driver>{745a17a0-74d3-11d0-b6fe-00a0c90f57da}\0012</Driver>
						<Class>HIDClass</Class>
						<Mfg>Microsoft</Mfg>
						<FriendlyName></FriendlyName>
						<ComPort></ComPort>
						<CompatIds></CompatIds>
					</DevInfo>
				</Device>
				<Device Desc="符合 HID 标准的供应商定义设备" DevInst="87" Lev="3">
					<DevInfo>
						<DevId>HID\IRDEVICEV2&amp;COL03\2&amp;2818A073&amp;0&amp;0002</DevId>
						<Driver>{745a17a0-74d3-11d0-b6fe-00a0c90f57da}\0013</Driver>
						<Class>HIDClass</Class>
						<Mfg>(标准系统设备)</Mfg>
						<FriendlyName></FriendlyName>
						<ComPort></ComPort>
						<CompatIds></CompatIds>
					</DevInfo>
				</Device>
				<Device Desc="符合 HID 标准的系统控制器" DevInst="88" Lev="3">
					<DevInfo>
						<DevId>HID\IRDEVICEV2&amp;COL04\2&amp;2818A073&amp;0&amp;0003</DevId>
						<Driver>{745a17a0-74d3-11d0-b6fe-00a0c90f57da}\0014</Driver>
						<Class>HIDClass</Class>
						<Mfg>(标准系统设备)</Mfg>
						<FriendlyName></FriendlyName>
						<ComPort></ComPort>
						<CompatIds></CompatIds>
					</DevInfo>
				</Device>
				<Device Desc="Microsoft eHome Remote Control Keyboard keys" DevInst="89" Lev="3">
					<DevInfo>
						<DevId>HID\IRDEVICEV2&amp;COL05\2&amp;2818A073&amp;0&amp;0004</DevId>
						<Driver>{4d36e96b-e325-11ce-bfc1-08002be10318}\0002</Driver>
						<Class>Keyboard</Class>
						<Mfg>Microsoft</Mfg>
						<FriendlyName></FriendlyName>
						<ComPort></ComPort>
						<CompatIds></CompatIds>
					</DevInfo>
				</Device>
				<Device Desc="Microsoft eHome MCIR Keyboard" DevInst="90" Lev="3">
					<DevInfo>
						<DevId>HID\IRDEVICEV2&amp;COL06\2&amp;2818A073&amp;0&amp;0005</DevId>
						<Driver>{4d36e96b-e325-11ce-bfc1-08002be10318}\0003</Driver>
						<Class>Keyboard</Class>
						<Mfg>Microsoft</Mfg>
						<FriendlyName></FriendlyName>
						<ComPort></ComPort>
						<CompatIds></CompatIds>
					</DevInfo>
				</Device>
				<Device Desc="Microsoft eHome MCIR 109 Keyboard" DevInst="91" Lev="3">
					<DevInfo>
						<DevId>HID\IRDEVICEV2&amp;COL07\2&amp;2818A073&amp;0&amp;0006</DevId>
						<Driver>{4d36e96b-e325-11ce-bfc1-08002be10318}\0004</Driver>
						<Class>Keyboard</Class>
						<Mfg>Microsoft</Mfg>
						<FriendlyName></FriendlyName>
						<ComPort></ComPort>
						<CompatIds></CompatIds>
					</DevInfo>
				</Device>
				<Device Desc="HID-compliant mouse" DevInst="92" Lev="3">
					<DevInfo>
						<DevId>HID\IRDEVICEV2&amp;COL08\2&amp;2818A073&amp;0&amp;0007</DevId>
						<Driver>{4d36e96f-e325-11ce-bfc1-08002be10318}\0001</Driver>
						<Class>Mouse</Class>
						<Mfg>Microsoft</Mfg>
						<FriendlyName></FriendlyName>
						<ComPort></ComPort>
						<CompatIds></CompatIds>
					</DevInfo>
				</Device>
			</Device>
		</Device>
		<Device Desc="Remote Desktop Device Redirector Bus" DevInst="93" Lev="1">
			<DevInfo>
				<DevId>ROOT\RDPBUS\0000</DevId>
				<Driver>{4d36e97d-e325-11ce-bfc1-08002be10318}\0004</Driver>
				<Class>System</Class>
				<Mfg>Microsoft</Mfg>
				<FriendlyName></FriendlyName>
				<ComPort></ComPort>
				<CompatIds></CompatIds>
			</DevInfo>
		</Device>
		<Device Desc="通用软件设备" DevInst="94" Lev="1">
			<DevInfo>
				<DevId>SWD\RADIO\{3DB5895D-CC28-44B3-AD3D-6F01A782B8D2}</DevId>
				<Driver>{62f9c741-b25a-46ce-b54c-9bccce08b6f2}\0002</Driver>
				<Class>SoftwareDevice</Class>
				<Mfg>Microsoft</Mfg>
				<FriendlyName>Microsoft Radio Device Enumeration Bus</FriendlyName>
				<ComPort></ComPort>
				<CompatIds>SWD\GenericRaw
SWD\Generic</CompatIds>
			</DevInfo>
			<Device Desc="通用软件设备" DevInst="95" Lev="2">
				<DevInfo>
					<DevId>SWD\RADIO\{E9BEE210-37D0-4FF1-B73E-53825A2E6991}</DevId>
					<Driver>{62f9c741-b25a-46ce-b54c-9bccce08b6f2}\0003</Driver>
					<Class>SoftwareDevice</Class>
					<Mfg>Microsoft</Mfg>
					<FriendlyName>WLAN 3</FriendlyName>
					<ComPort></ComPort>
					<CompatIds>SWD\GenericRaw
SWD\Generic</CompatIds>
				</DevInfo>
			</Device>
		</Device>
		<Device Desc="通用软件设备" DevInst="96" Lev="1">
			<DevInfo>
				<DevId>SWD\MMDEVAPI\MICROSOFTGSWAVETABLESYNTH</DevId>
				<Driver>{62f9c741-b25a-46ce-b54c-9bccce08b6f2}\0000</Driver>
				<Class>SoftwareDevice</Class>
				<Mfg>Microsoft</Mfg>
				<FriendlyName>Microsoft GS 波表合成器</FriendlyName>
				<ComPort></ComPort>
				<CompatIds>SWD\GenericRaw
SWD\Generic</CompatIds>
			</DevInfo>
		</Device>
		<Device Desc="通用软件设备" DevInst="97" Lev="1">
			<DevInfo>
				<DevId>SWD\MSDAS\{CE958E9A-424F-4C88-86F4-11314821E75A}</DevId>
				<Driver>{62f9c741-b25a-46ce-b54c-9bccce08b6f2}\0001</Driver>
				<Class>SoftwareDevice</Class>
				<Mfg>Microsoft</Mfg>
				<FriendlyName>Microsoft Device Association Root Enumerator</FriendlyName>
				<ComPort></ComPort>
				<CompatIds>SWD\GenericRaw
SWD\Generic</CompatIds>
			</DevInfo>
		</Device>
		<Device Desc="通用软件设备" DevInst="98" Lev="1">
			<DevInfo>
				<DevId>SWD\IP_TUNNEL_VBUS\IP_TUNNEL_DEVICE_ROOT</DevId>
				<Driver>{62f9c741-b25a-46ce-b54c-9bccce08b6f2}\0004</Driver>
				<Class>SoftwareDevice</Class>
				<Mfg>Microsoft</Mfg>
				<FriendlyName>Microsoft IPv4 IPv6 转换适配器总线</FriendlyName>
				<ComPort></ComPort>
				<CompatIds>SWD\GenericRaw
SWD\Generic</CompatIds>
			</DevInfo>
			<Device Desc="Microsoft Teredo Tunneling Adapter" DevInst="99" Lev="2">
				<DevInfo>
					<DevId>SWD\IP_TUNNEL_VBUS\TEREDO_TUNNEL_DEVICE</DevId>
					<Driver>{4d36e972-e325-11ce-bfc1-08002be10318}\0007</Driver>
					<Class>Net</Class>
					<Mfg>Microsoft</Mfg>
					<FriendlyName>Microsoft Teredo Tunneling Adapter</FriendlyName>
					<ComPort></ComPort>
					<CompatIds>SWD\GenericRaw
SWD\Generic</CompatIds>
				</DevInfo>
			</Device>
			<Device Desc="Microsoft ISATAP Adapter" DevInst="100" Lev="2">
				<DevInfo>
					<DevId>SWD\IP_TUNNEL_VBUS\ISATAP_1</DevId>
					<Driver>{4d36e972-e325-11ce-bfc1-08002be10318}\0008</Driver>
					<Class>Net</Class>
					<Mfg>Microsoft</Mfg>
					<FriendlyName>Microsoft ISATAP Adapter #2</FriendlyName>
					<ComPort></ComPort>
					<CompatIds>SWD\GenericRaw
SWD\Generic</CompatIds>
				</DevInfo>
			</Device>
		</Device>
		<Device Desc="本地打印队列" DevInst="101" Lev="1">
			<DevInfo>
				<DevId>SWD\PRINTENUM\PRINTQUEUES</DevId>
				<Driver>{1ed2bbf9-11f0-4084-b21f-ad83a8e6dcdc}\0000</Driver>
				<Class>PrintQueue</Class>
				<Mfg>Microsoft</Mfg>
				<FriendlyName>根打印队列</FriendlyName>
				<ComPort></ComPort>
				<CompatIds>SWD\GenericRaw
SWD\Generic</CompatIds>
			</DevInfo>
			<Device Desc="本地打印队列" DevInst="102" Lev="2">
				<DevInfo>
					<DevId>SWD\PRINTENUM\{6D6C68BE-0F23-48FB-88C0-F2CF595E59F7}</DevId>
					<Driver>{1ed2bbf9-11f0-4084-b21f-ad83a8e6dcdc}\0001</Driver>
					<Class>PrintQueue</Class>
					<Mfg>Microsoft</Mfg>
					<FriendlyName>Microsoft Print to PDF</FriendlyName>
					<ComPort></ComPort>
					<CompatIds>GenPrintQueue
SWD\GenericRaw
SWD\Generic</CompatIds>
				</DevInfo>
			</Device>
		</Device>
		<Device Desc="通用软件设备" DevInst="103" Lev="1">
			<DevInfo>
				<DevId>SWD\MSRRAS\{5E259276-BC7E-40E3-B93B-8F89B5F3ABC0}</DevId>
				<Driver>{62f9c741-b25a-46ce-b54c-9bccce08b6f2}\0005</Driver>
				<Class>SoftwareDevice</Class>
				<Mfg>Microsoft</Mfg>
				<FriendlyName>Microsoft RRAS Root Enumerator</FriendlyName>
				<ComPort></ComPort>
				<CompatIds>SWD\GenericRaw
SWD\Generic</CompatIds>
			</DevInfo>
			<Device Desc="WAN 微型端口(SSTP)" DevInst="104" Lev="2">
				<DevInfo>
					<DevId>SWD\MSRRAS\MS_SSTPMINIPORT</DevId>
					<Driver>{4d36e972-e325-11ce-bfc1-08002be10318}\0009</Driver>
					<Class>Net</Class>
					<Mfg>Microsoft</Mfg>
					<FriendlyName>WAN Miniport (SSTP)</FriendlyName>
					<ComPort></ComPort>
					<CompatIds>SWD\Generic</CompatIds>
				</DevInfo>
			</Device>
			<Device Desc="WAN Miniport (IKEv2)" DevInst="105" Lev="2">
				<DevInfo>
					<DevId>SWD\MSRRAS\MS_AGILEVPNMINIPORT</DevId>
					<Driver>{4d36e972-e325-11ce-bfc1-08002be10318}\0010</Driver>
					<Class>Net</Class>
					<Mfg>Microsoft</Mfg>
					<FriendlyName>WAN Miniport (IKEv2)</FriendlyName>
					<ComPort></ComPort>
					<CompatIds>SWD\Generic</CompatIds>
				</DevInfo>
			</Device>
			<Device Desc="WAN Miniport (L2TP)" DevInst="106" Lev="2">
				<DevInfo>
					<DevId>SWD\MSRRAS\MS_L2TPMINIPORT</DevId>
					<Driver>{4d36e972-e325-11ce-bfc1-08002be10318}\0011</Driver>
					<Class>Net</Class>
					<Mfg>Microsoft</Mfg>
					<FriendlyName>WAN Miniport (L2TP)</FriendlyName>
					<ComPort></ComPort>
					<CompatIds>SWD\Generic</CompatIds>
				</DevInfo>
			</Device>
			<Device Desc="WAN Miniport (PPTP)" DevInst="107" Lev="2">
				<DevInfo>
					<DevId>SWD\MSRRAS\MS_PPTPMINIPORT</DevId>
					<Driver>{4d36e972-e325-11ce-bfc1-08002be10318}\0012</Driver>
					<Class>Net</Class>
					<Mfg>Microsoft</Mfg>
					<FriendlyName>WAN Miniport (PPTP)</FriendlyName>
					<ComPort></ComPort>
					<CompatIds>SWD\Generic</CompatIds>
				</DevInfo>
			</Device>
			<Device Desc="WAN Miniport (PPPOE)" DevInst="108" Lev="2">
				<DevInfo>
					<DevId>SWD\MSRRAS\MS_PPPOEMINIPORT</DevId>
					<Driver>{4d36e972-e325-11ce-bfc1-08002be10318}\0013</Driver>
					<Class>Net</Class>
					<Mfg>Microsoft</Mfg>
					<FriendlyName>WAN Miniport (PPPOE)</FriendlyName>
					<ComPort></ComPort>
					<CompatIds>SWD\Generic</CompatIds>
				</DevInfo>
			</Device>
			<Device Desc="WAN Miniport (IP)" DevInst="109" Lev="2">
				<DevInfo>
					<DevId>SWD\MSRRAS\MS_NDISWANIP</DevId>
					<Driver>{4d36e972-e325-11ce-bfc1-08002be10318}\0014</Driver>
					<Class>Net</Class>
					<Mfg>Microsoft</Mfg>
					<FriendlyName>WAN Miniport (IP)</FriendlyName>
					<ComPort></ComPort>
					<CompatIds>SWD\Generic</CompatIds>
				</DevInfo>
			</Device>
			<Device Desc="WAN Miniport (IPv6)" DevInst="110" Lev="2">
				<DevInfo>
					<DevId>SWD\MSRRAS\MS_NDISWANIPV6</DevId>
					<Driver>{4d36e972-e325-11ce-bfc1-08002be10318}\0015</Driver>
					<Class>Net</Class>
					<Mfg>Microsoft</Mfg>
					<FriendlyName>WAN Miniport (IPv6)</FriendlyName>
					<ComPort></ComPort>
					<CompatIds>SWD\Generic</CompatIds>
				</DevInfo>
			</Device>
			<Device Desc="WAN Miniport (Network Monitor)" DevInst="111" Lev="2">
				<DevInfo>
					<DevId>SWD\MSRRAS\MS_NDISWANBH</DevId>
					<Driver>{4d36e972-e325-11ce-bfc1-08002be10318}\0016</Driver>
					<Class>Net</Class>
					<Mfg>Microsoft</Mfg>
					<FriendlyName>WAN Miniport (Network Monitor)</FriendlyName>
					<ComPort></ComPort>
					<CompatIds>SWD\Generic</CompatIds>
				</DevInfo>
			</Device>
		</Device>
		<Device Desc="Virtual Serial Bus Enumerator 7 (Eltima Software)" DevInst="112" Lev="1">
			<DevInfo>
				<DevId>ROOT\SYSTEM\0002</DevId>
				<Driver>{4d36e97d-e325-11ce-bfc1-08002be10318}\0034</Driver>
				<Class>System</Class>
				<Mfg>ELTIMA Software</Mfg>
				<FriendlyName></FriendlyName>
				<ComPort></ComPort>
				<CompatIds></CompatIds>
			</DevInfo>
			<Device Desc="Virtual Serial Port 7 (Eltima Software)" DevInst="113" Lev="2">
				<DevInfo>
					<DevId>VSBC7\DEVICES\0000</DevId>
					<Driver>{13b66731-2122-4dac-831e-c60e713ff306}\0000</Driver>
					<Class>EVSPorts7</Class>
					<Mfg>ELTIMA Software</Mfg>
					<FriendlyName>ELTIMA Virtual Serial Port (COM20-&gt;COM40)</FriendlyName>
					<ComPort>COM20</ComPort>
					<CompatIds>*ELTIMACompatibleVSDBus</CompatIds>
				</DevInfo>
			</Device>
			<Device Desc="Virtual Serial Port 7 (Eltima Software)" DevInst="114" Lev="2">
				<DevInfo>
					<DevId>VSBC7\DEVICES\0001</DevId>
					<Driver>{13b66731-2122-4dac-831e-c60e713ff306}\0001</Driver>
					<Class>EVSPorts7</Class>
					<Mfg>ELTIMA Software</Mfg>
					<FriendlyName>ELTIMA Virtual Serial Port (COM40-&gt;COM20)</FriendlyName>
					<ComPort>COM40</ComPort>
					<CompatIds>*ELTIMACompatibleVSDBus</CompatIds>
				</DevInfo>
			</Device>
		</Device>
	</Device>
</DeviceTree>
